README.md
setup.py
bin/fes-control
fes/__init__.py
fes/server-test.py
fes/server.py
fes.egg-info/PKG-INFO
fes.egg-info/SOURCES.txt
fes.egg-info/dependency_links.txt
fes.egg-info/requires.txt
fes.egg-info/top_level.txt