Metadata-Version: 2.1
Name: fes
Version: 1.0.62
Summary: UNKNOWN
Home-page: https://www.altertech.com/products/fes/
Author: Altertech
Author-email: div@altertech.com
License: Propietary
Platform: UNKNOWN
Classifier: Programming Language :: Python :: 3
